{
    "name": "S_schneider",
    "data_format": "json",
    "normalization_file": "label_range_scaled.json",
    "normalization_keys": {
        "minmax_min": "minmax_min_vroom_scaled",
        "minmax_max": "minmax_max_vroom_scaled",
        "cost_over_fi_minmax_min": "cost_over_fi_minmax_min_vroom_scaled",
        "cost_over_fi_minmax_max": "cost_over_fi_minmax_max_vroom_scaled"
    },
    "solver_timeout": 3600,
    "vroom_timeout": 5,
    "ortools_timeout": 5,
    "vrpeasy_timeout": 3600,
    "extra_normalization_modes": []
}